flake8_no_fstring
