Metadata-Version: 2.1
Name: flake8-no-fstring
Version: 1.0.1
Summary: A flake8 plugin to ban f-strings
Home-page: https://github.com/seporaitis/flake8-no-fstring
Author: Julius Seporaitis
Author-email: julius@seporaitis.net
License: ISCL
Project-URL: Changelog, https://github.com/seporaitis/flake8-no-fstring/blob/master/HISTORY.rst
Keywords: flake8
Platform: UNKNOWN
Classifier: Development Status :: 5 - Production/Stable
Classifier: Framework :: Flake8
Classifier: Intended Audience :: Developers
Classifier: License :: OSI Approved :: ISC License (ISCL)
Classifier: Natural Language :: English
Classifier: Programming Language :: Python :: 3 :: Only
Classifier: Programming Language :: Python :: 3
Classifier: Programming Language :: Python :: 3.6
Classifier: Programming Language :: Python :: 3.7
Classifier: Programming Language :: Python :: 3.8
Classifier: Programming Language :: Python :: 3.9
Requires-Python: >=3.6
